Workbook

Sheet Summary
A1: Developer Pro Forma Summary
A2: AQUILA / Hope Alliance lease-purchase option economics based on $16M all-in cost and 9% initial yield.
A4: Key Assumption | B4: Value
A5: Facility Size | B5: =Assumptions!B6 -> 47000
A6: All-In Project Cost | B6: =Assumptions!B7 -> 16000000
A7: Initial Rent Yield | B7: =Assumptions!B8 -> 0.09
A8: Year 1 Annual Rent | B8: =Assumptions!B11 -> 1440000
A9: Annual Escalation | B9: =Assumptions!B9 -> 0.02
A10: Senior Debt | B10: =Assumptions!B14 -> 12500000
A11: Developer Equity | B11: =Assumptions!B15 -> 3500000
A12: Debt Rate | B12: =Assumptions!B16 -> 0.07
A13: Annual Debt Interest | B13: =Assumptions!B17 -> 875000
A16: Hope Alliance Purchase Option Scenarios
A17: Option Year | B17: Gross Option Price | C17: Rent Credit | D17: Net Purchase Price | E17: Net Sale Proceeds After Debt | F17: Cash Flow During Hold | G17: Developer Profit | H17: Equity Multiple | I17: Leveraged IRR
A18: ='Purchase Options'!A5 -> 3 | B18: ='Purchase Options'!B5 -> 18500000 | C18: ='Purchase Options'!C5 -> 440697.6 | D18: ='Purchase Options'!D5 -> 18059302 | E18: ='Purchase Options'!E5 -> 5559302.4 | F18: ='Purchase Options'!F5 -> 1781976 | G18: ='Purchase Options'!G5 -> 3841278.4 | H18: ='Purchase Options'!H5 -> 2.0975081 | I18: ='Purchase Options'!I5 -> 0.31385316
A19: ='Purchase Options'!A6 -> 5 | B19: ='Purchase Options'!B6 -> 18000000 | C19: ='Purchase Options'!C6 -> 903723.87 | D19: ='Purchase Options'!D6 -> 17096276 | E19: ='Purchase Options'!E6 -> 4596276.1 | F19: ='Purchase Options'!F6 -> 3118817.8 | G19: ='Purchase Options'!G6 -> 4215094 | H19: ='Purchase Options'!H6 -> 2.2043126 | I19: ='Purchase Options'!I6 -> 0.21577025
A20: ='Purchase Options'!A7 -> 7 | B20: ='Purchase Options'!B7 -> 17500000 | C20: ='Purchase Options'!C7 -> 1385456.4 | D20: ='Purchase Options'!D7 -> 16114544 | E20: ='Purchase Options'!E7 -> 3614543.6 | F20: ='Purchase Options'!F7 -> 4580368.1 | G20: ='Purchase Options'!G7 -> 4694911.7 | H20: ='Purchase Options'!H7 -> 2.3414033 | I20: ='Purchase Options'!I7 -> 0.18392354
A23: Outside Sale After Year 7 Scenarios
A24: Exit Cap Rate | B24: Year 8 Rent | C24: Sale Price | D24: Debt Payoff | E24: Net Sale Proceeds | F24: 7-Year Cash Flow | G24: Developer Profit | H24: Equity Multiple | I24: Leveraged IRR
A25: ='Outside Sale'!A5 -> 0.085 | B25: ='Outside Sale'!B5 -> 1654107.4 | C25: ='Outside Sale'!C5 -> 19460087 | D25: ='Outside Sale'!D5 -> 12500000 | E25: ='Outside Sale'!E5 -> 6960086.6 | F25: ='Outside Sale'!F5 -> 4580368.1 | G25: ='Outside Sale'!G5 -> 8040454.7 | H25: ='Outside Sale'!H5 -> 3.2972728 | I25: ='Outside Sale'!I5 -> 0.24604686
A26: ='Outside Sale'!A6 -> 0.08 | B26: ='Outside Sale'!B6 -> 1654107.4 | C26: ='Outside Sale'!C6 -> 20676342 | D26: ='Outside Sale'!D6 -> 12500000 | E26: ='Outside Sale'!E6 -> 8176342 | F26: ='Outside Sale'!F6 -> 4580368.1 | G26: ='Outside Sale'!G6 -> 9256710.1 | H26: ='Outside Sale'!H6 -> 3.6447743 | I26: ='Outside Sale'!I6 -> 0.26408965
A27: ='Outside Sale'!A7 -> 0.075 | B27: ='Outside Sale'!B7 -> 1654107.4 | C27: ='Outside Sale'!C7 -> 22054765 | D27: ='Outside Sale'!D7 -> 12500000 | E27: ='Outside Sale'!E7 -> 9554764.8 | F27: ='Outside Sale'!F7 -> 4580368.1 | G27: ='Outside Sale'!G7 -> 10635133 | H27: ='Outside Sale'!H7 -> 4.0386094 | I27: ='Outside Sale'!I7 -> 0.28258637

Sheet Assumptions
A1: AQUILA / Hope Alliance Development Pro Forma
A2: Inputs are based on the proposed lease-purchase option structure and user-provided assumptions.
A4: Project and Lease Assumptions
A5: Input | B5: Value | C5: Units / Format | D5: Source / Notes | E5: Cell Ref | F5: Editable?
A6: Facility Size | B6: 47000 | C6: SF | D6: User-provided project size | E6: B6 | F6: Yes
A7: All-In Project Cost | B7: 16000000 | C7: $ | D7: User-provided all-in cost; includes land, hard costs, soft costs, contingency, and financing costs per discussion | E7: B7 | F7: Yes
A8: Year 1 Rent Yield | B8: 0.09 | C8: % | D8: User requested 9.0% yield on $16M cost | E8: B8 | F8: Yes
A9: Annual Rent Escalation | B9: 0.02 | C9: % | D9: Proposed annual lease escalation | E9: B9 | F9: Yes
A10: Lease Term | B10: 20 | C10: Years | D10: Proposed long-term lease term | E10: B10 | F10: Yes
A11: Year 1 Annual Rent | B11: =B7*B8 -> 1440000 | C11: $ | D11: Formula: All-in cost x rent yield | E11: B11 | F11: No
A12: Year 1 Monthly Rent | B12: =B11/12 -> 120000 | C12: $ | D12: Formula: annual rent / 12 | E12: B12 | F12: No
A13: Initial Rent PSF | B13: =B11/B6 -> 30.638298 | C13: $/SF/Yr | D13: Formula: annual rent / facility SF | E13: B13 | F13: No
A14: Senior Debt | B14: 12500000 | C14: $ | D14: Developer capital stack assumption | E14: B14 | F14: Yes
A15: Developer Equity | B15: =B7-B14 -> 3500000 | C15: $ | D15: Formula: all-in cost less senior debt | E15: B15 | F15: No
A16: Debt Rate | B16: 0.07 | C16: % | D16: Assumed interest-only debt rate | E16: B16 | F16: Yes
A17: Annual Debt Interest | B17: =B14*B16 -> 875000 | C17: $ | D17: Formula: debt x rate | E17: B17 | F17: No
A18: Rent Credit Years 1-3 | B18: 0.1 | C18: % | D18: User requested rent credit for years 1-3 | E18: B18 | F18: Yes
A19: Rent Credit Years 4-7 | B19: 0.15 | C19: % | D19: User requested rent credit for years 4-7 | E19: B19 | F19: Yes
A20: Year 3 Gross Option Price | B20: 18500000 | C20: $ | D20: Negotiated gross purchase option price before credits | E20: B20 | F20: Yes
A21: Year 5 Gross Option Price | B21: 18000000 | C21: $ | D21: Negotiated gross purchase option price before credits | E21: B21 | F21: Yes
A22: Year 7 Gross Option Price | B22: 17500000 | C22: $ | D22: Negotiated gross purchase option price before credits | E22: B22 | F22: Yes

Sheet Lease Credits
A1: Lease Schedule and Rent Credits
A2: Rent, rent credits, and annual cash flow to developer through Year 7.
A4: Year | B4: Annual Rent | C4: Monthly Rent | D4: Credit % | E4: Annual Credit | F4: Cumulative Credit | G4: Cash Flow to Developer | H4: Notes
A5: 1 | B5: =Assumptions!$B$11 -> 1440000 | C5: =B5/12 -> 120000 | D5: =IF(A5<=3,Assumptions!$B$18,Assumptions!$B$19) -> 0.1 | E5: =B5*D5 -> 144000 | F5: =SUM($E$5:E5) -> 144000 | G5: =B5-Assumptions!$B$17 -> 565000 | H5: Year 1 rent based on 9% yield
A6: 2 | B6: =B5*(1+Assumptions!$B$9) -> 1468800 | C6: =B6/12 -> 122400 | D6: =IF(A6<=3,Assumptions!$B$18,Assumptions!$B$19) -> 0.1 | E6: =B6*D6 -> 146880 | F6: =SUM($E$5:E6) -> 290880 | G6: =B6-Assumptions!$B$17 -> 593800 | H6: 2% annual escalation
A7: 3 | B7: =B6*(1+Assumptions!$B$9) -> 1498176 | C7: =B7/12 -> 124848 | D7: =IF(A7<=3,Assumptions!$B$18,Assumptions!$B$19) -> 0.1 | E7: =B7*D7 -> 149817.6 | F7: =SUM($E$5:E7) -> 440697.6 | G7: =B7-Assumptions!$B$17 -> 623176 | H7: 10% rent credit
A8: 4 | B8: =B7*(1+Assumptions!$B$9) -> 1528139.5 | C8: =B8/12 -> 127344.96 | D8: =IF(A8<=3,Assumptions!$B$18,Assumptions!$B$19) -> 0.15 | E8: =B8*D8 -> 229220.93 | F8: =SUM($E$5:E8) -> 669918.53 | G8: =B8-Assumptions!$B$17 -> 653139.52 | H8: 15% rent credit begins
A9: 5 | B9: =B8*(1+Assumptions!$B$9) -> 1558702.3 | C9: =B9/12 -> 129891.86 | D9: =IF(A9<=3,Assumptions!$B$18,Assumptions!$B$19) -> 0.15 | E9: =B9*D9 -> 233805.35 | F9: =SUM($E$5:E9) -> 903723.87 | G9: =B9-Assumptions!$B$17 -> 683702.31 | H9: Year 5 option date
A10: 6 | B10: =B9*(1+Assumptions!$B$9) -> 1589876.4 | C10: =B10/12 -> 132489.7 | D10: =IF(A10<=3,Assumptions!$B$18,Assumptions!$B$19) -> 0.15 | E10: =B10*D10 -> 238481.45 | F10: =SUM($E$5:E10) -> 1142205.3 | G10: =B10-Assumptions!$B$17 -> 714876.36 | H10: Year 6 hold
A11: 7 | B11: =B10*(1+Assumptions!$B$9) -> 1621673.9 | C11: =B11/12 -> 135139.49 | D11: =IF(A11<=3,Assumptions!$B$18,Assumptions!$B$19) -> 0.15 | E11: =B11*D11 -> 243251.08 | F11: =SUM($E$5:E11) -> 1385456.4 | G11: =B11-Assumptions!$B$17 -> 746673.88 | H11: Year 7 option date

Sheet Purchase Options
A1: Purchase Option Return Analysis
A2: Developer returns if Hope Alliance exercises the purchase option in Year 3, Year 5, or Year 7.
A4: Option Year | B4: Gross Option Price | C4: Rent Credit | D4: Net Purchase Price | E4: Net Sale Proceeds After Debt | F4: Cash Flow During Hold | G4: Developer Profit | H4: Equity Multiple | I4: Leveraged IRR | J4: Year 0 | K4: Year 1 | L4: Year 2 | M4: Year 3 | N4: Year 4 | O4: Year 5 | P4: Year 6 | Q4: Year 7
A5: 3 | B5: =Assumptions!$B$20 -> 18500000 | C5: ='Lease Credits'!F7 -> 440697.6 | D5: =B5-C5 -> 18059302 | E5: =D5-Assumptions!$B$14 -> 5559302.4 | F5: =SUM('Lease Credits'!$G$5:$G$7) -> 1781976 | G5: =E5+F5-Assumptions!$B$15 -> 3841278.4 | H5: =(E5+F5)/Assumptions!$B$15 -> 2.0975081 | I5: =IRR(J5:M5) -> 0.31385316 | J5: =-Assumptions!$B$15 -> -3500000 | K5: ='Lease Credits'!G5 -> 565000 | L5: ='Lease Credits'!G6 -> 593800 | M5: ='Lease Credits'!G7+E5 -> 6182478.4
A6: 5 | B6: =Assumptions!$B$21 -> 18000000 | C6: ='Lease Credits'!F9 -> 903723.87 | D6: =B6-C6 -> 17096276 | E6: =D6-Assumptions!$B$14 -> 4596276.1 | F6: =SUM('Lease Credits'!$G$5:$G$9) -> 3118817.8 | G6: =E6+F6-Assumptions!$B$15 -> 4215094 | H6: =(E6+F6)/Assumptions!$B$15 -> 2.2043126 | I6: =IRR(J6:O6) -> 0.21577025 | J6: =-Assumptions!$B$15 -> -3500000 | K6: ='Lease Credits'!G5 -> 565000 | L6: ='Lease Credits'!G6 -> 593800 | M6: ='Lease Credits'!G7 -> 623176 | N6: ='Lease Credits'!G8 -> 653139.52 | O6: ='Lease Credits'!G9+E6 -> 5279978.4
A7: 7 | B7: =Assumptions!$B$22 -> 17500000 | C7: ='Lease Credits'!F11 -> 1385456.4 | D7: =B7-C7 -> 16114544 | E7: =D7-Assumptions!$B$14 -> 3614543.6 | F7: =SUM('Lease Credits'!$G$5:$G$11) -> 4580368.1 | G7: =E7+F7-Assumptions!$B$15 -> 4694911.7 | H7: =(E7+F7)/Assumptions!$B$15 -> 2.3414033 | I7: =IRR(J7:Q7) -> 0.18392354 | J7: =-Assumptions!$B$15 -> -3500000 | K7: ='Lease Credits'!G5 -> 565000 | L7: ='Lease Credits'!G6 -> 593800 | M7: ='Lease Credits'!G7 -> 623176 | N7: ='Lease Credits'!G8 -> 653139.52 | O7: ='Lease Credits'!G9 -> 683702.31 | P7: ='Lease Credits'!G10 -> 714876.36 | Q7: ='Lease Credits'!G11+E7 -> 4361217.5

Sheet Outside Sale
A1: Outside Sale Scenario After Year 7
A2: Assumes Hope Alliance does not exercise the Year 7 option; rent credits expire and AQUILA sells the leased asset.
A4: Exit Cap Rate | B4: Year 8 Rent | C4: Sale Price | D4: Debt Payoff | E4: Net Sale Proceeds | F4: 7-Year Cash Flow | G4: Developer Profit | H4: Equity Multiple | I4: Leveraged IRR | J4: Year 0 | K4: Year 1 | L4: Year 2 | M4: Year 3 | N4: Year 4 | O4: Year 5 | P4: Year 6 | Q4: Year 7
A5: 0.085 | B5: ='Lease Credits'!B11*(1+Assumptions!$B$9) -> 1654107.4 | C5: =B5/A5 -> 19460087 | D5: =Assumptions!$B$14 -> 12500000 | E5: =C5-D5 -> 6960086.6 | F5: =SUM('Lease Credits'!$G$5:$G$11) -> 4580368.1 | G5: =E5+F5-Assumptions!$B$15 -> 8040454.7 | H5: =(E5+F5)/Assumptions!$B$15 -> 3.2972728 | I5: =IRR(J5:Q5) -> 0.24604686 | J5: =-Assumptions!$B$15 -> -3500000 | K5: ='Lease Credits'!G5 -> 565000 | L5: ='Lease Credits'!G6 -> 593800 | M5: ='Lease Credits'!G7 -> 623176 | N5: ='Lease Credits'!G8 -> 653139.52 | O5: ='Lease Credits'!G9 -> 683702.31 | P5: ='Lease Credits'!G10 -> 714876.36 | Q5: ='Lease Credits'!G11+E5 -> 7706760.5
A6: 0.08 | B6: ='Lease Credits'!B11*(1+Assumptions!$B$9) -> 1654107.4 | C6: =B6/A6 -> 20676342 | D6: =Assumptions!$B$14 -> 12500000 | E6: =C6-D6 -> 8176342 | F6: =SUM('Lease Credits'!$G$5:$G$11) -> 4580368.1 | G6: =E6+F6-Assumptions!$B$15 -> 9256710.1 | H6: =(E6+F6)/Assumptions!$B$15 -> 3.6447743 | I6: =IRR(J6:Q6) -> 0.26408965 | J6: =-Assumptions!$B$15 -> -3500000 | K6: ='Lease Credits'!G5 -> 565000 | L6: ='Lease Credits'!G6 -> 593800 | M6: ='Lease Credits'!G7 -> 623176 | N6: ='Lease Credits'!G8 -> 653139.52 | O6: ='Lease Credits'!G9 -> 683702.31 | P6: ='Lease Credits'!G10 -> 714876.36 | Q6: ='Lease Credits'!G11+E6 -> 8923015.9
A7: 0.075 | B7: ='Lease Credits'!B11*(1+Assumptions!$B$9) -> 1654107.4 | C7: =B7/A7 -> 22054765 | D7: =Assumptions!$B$14 -> 12500000 | E7: =C7-D7 -> 9554764.8 | F7: =SUM('Lease Credits'!$G$5:$G$11) -> 4580368.1 | G7: =E7+F7-Assumptions!$B$15 -> 10635133 | H7: =(E7+F7)/Assumptions!$B$15 -> 4.0386094 | I7: =IRR(J7:Q7) -> 0.28258637 | J7: =-Assumptions!$B$15 -> -3500000 | K7: ='Lease Credits'!G5 -> 565000 | L7: ='Lease Credits'!G6 -> 593800 | M7: ='Lease Credits'!G7 -> 623176 | N7: ='Lease Credits'!G8 -> 653139.52 | O7: ='Lease Credits'!G9 -> 683702.31 | P7: ='Lease Credits'!G10 -> 714876.36 | Q7: ='Lease Credits'!G11+E7 -> 10301439

Sheet Sources & Notes
A1: Sources & Notes
A2: User-provided inputs and model conventions.
A4: Topic | B4: Source / Note | C4: Impact | D4: Update Needed?
A5: Project Size | B5: 47,000 SF provided by user for Hope Alliance Cedar Park facility. | C5: Drives cost per SF and rent PSF. | D5: Confirm
A6: All-In Cost | B6: $16,000,000 all-in cost confirmed by user. | C6: Base for 9% yield and purchase option premium. | D6: Confirm with GC/development budget
A7: Rent Yield | B7: User requested 9% yield based on $16M all-in cost. | C7: Sets Year 1 annual rent at $1.44M. | D7: Confirm with Hope Alliance
A8: Rent Credits | B8: User requested 10% rent credit for Years 1-3 and 15% for Years 4-7. | C8: Reduces net purchase price if Hope Alliance closes on option. | D8: Include in LOI
A9: Option Prices | B9: $18.5M Year 3, $18.0M Year 5, $17.5M Year 7 from agreed working scenarios. | C9: Defines negotiated lease-purchase path. | D9: Confirm before sending
A10: Debt Assumption | B10: $12.5M senior debt at 7.0% interest-only used for internal developer analysis. | C10: Drives developer cash flow and IRR. | D10: Update with lender quotes
A11: Credit Expiration | B11: Model assumes rent credits expire if Hope Alliance does not exercise and close. | C11: Preserves outside sale value for AQUILA. | D11: Critical legal protection
A12: Taxes / Transaction Costs | B12: Model excludes closing costs, taxes, reserves, leasing costs, capex, and income taxes unless added later. | C12: Actual returns will vary. | D12: Add in detailed underwriting
